ecr_sync/__init__.py
ecr_sync/__main__.py
ecr_sync-2.0.0.dist-info/METADATA
ecr_sync-2.0.0.dist-info/WHEEL
ecr_sync-2.0.0.dist-info/entry_points.txt
ecr_sync-2.0.0.dist-info/RECORD
