Metadata-Version: 2.1
Name: ecr_sync
Version: 2.0.0
Summary: Mirror and synchronize OCI Docker images to ECR repositories
License: MIT
Keywords: docker,ecr,mirror,sync
Author: Tom Forbes
Author-email: tom.forbes@onfido.com
Requires-Python: >=3.10,<4.0
Classifier: License :: OSI Approved :: MIT License
Classifier: Programming Language :: Python :: 3
Classifier: Programming Language :: Python :: 3.10
Classifier: Programming Language :: Python :: 3.11
Classifier: Programming Language :: Python :: 3.12
Requires-Dist: boto3
Requires-Dist: boto3-stubs[ecr,ecr-public]
Requires-Dist: click
